newdatatypes/__init__.py
newdatatypes_1.0.0-1.0.0.dist-info/METADATA
newdatatypes_1.0.0-1.0.0.dist-info/WHEEL
newdatatypes_1.0.0-1.0.0.dist-info/top_level.txt
newdatatypes_1.0.0-1.0.0.dist-info/RECORD
